[
  {
    "topic": "What if Earth stopped spinning for a day?",
    "tone": "explainer",
    "style": "Educational with a slightly humorous, engaging delivery",
    "priority": 5,
    "created_at": "2025-08-24T05:05:25.739836",
    "account": "Physics"
  },
  {
    "topic": "How does gravity work in space?",
    "tone": "explainer",
    "style": "Educational with a slightly humorous, engaging delivery",
    "priority": 5,
    "created_at": "2025-08-24T05:05:25.739836",
    "account": "Physics"
  },
  {
    "topic": "Can you really bend light with a glass?",
    "tone": "explainer",
    "style": "Educational with a slightly humorous, engaging delivery",
    "priority": 5,
    "created_at": "2025-08-24T05:05:25.739836",
    "account": "Physics"
  },
  {
    "topic": "What happens if you fall into a black hole?",
    "tone": "explainer",
    "style": "Educational with a slightly humorous, engaging delivery",
    "priority": 5,
    "created_at": "2025-08-24T05:05:25.739836",
    "account": "Physics"
  },
  {
    "topic": "Why do we feel dizzy on a merry-go-round?",
    "tone": "explainer",
    "style": "Educational with a slightly humorous, engaging delivery",
    "priority": 5,
    "created_at": "2025-08-24T05:05:25.739836",
    "account": "Physics"
  },
  {
    "topic": "What\u2019s the deal with time travel in physics?",
    "tone": "explainer",
    "style": "Educational with a slightly humorous, engaging delivery",
    "priority": 5,
    "created_at": "2025-08-24T05:05:25.739836",
    "account": "Physics"
  },
  {
    "topic": "How do planes stay up in the air?",
    "tone": "explainer",
    "style": "Educational with a slightly humorous, engaging delivery",
    "priority": 5,
    "created_at": "2025-08-24T05:05:25.739836",
    "account": "Physics"
  },
  {
    "topic": "Why do cats always land on their feet?",
    "tone": "explainer",
    "style": "Educational with a slightly humorous, engaging delivery",
    "priority": 5,
    "created_at": "2025-08-24T05:05:25.739836",
    "account": "Physics"
  },
  {
    "topic": "What if we could see sound waves?",
    "tone": "explainer",
    "style": "Educational with a slightly humorous, engaging delivery",
    "priority": 5,
    "created_at": "2025-08-24T05:05:25.739836",
    "account": "Physics"
  },
  {
    "topic": "How does a microwave heat food?",
    "tone": "explainer",
    "style": "Educational with a slightly humorous, engaging delivery",
    "priority": 5,
    "created_at": "2025-08-24T05:05:25.739836",
    "account": "Physics"
  },
  {
    "topic": "What is the physics behind a rainbow?",
    "tone": "explainer",
    "style": "Educational with a slightly humorous, engaging delivery",
    "priority": 5,
    "created_at": "2025-08-24T05:05:25.739836",
    "account": "Physics"
  },
  {
    "topic": "Why do we float in water?",
    "tone": "explainer",
    "style": "Educational with a slightly humorous, engaging delivery",
    "priority": 5,
    "created_at": "2025-08-24T05:05:25.739836",
    "account": "Physics"
  },
  {
    "topic": "How does a compass know north?",
    "tone": "explainer",
    "style": "Educational with a slightly humorous, engaging delivery",
    "priority": 5,
    "created_at": "2025-08-24T05:05:25.739836",
    "account": "Physics"
  },
  {
    "topic": "What would happen if the sun disappeared?",
    "tone": "explainer",
    "style": "Educational with a slightly humorous, engaging delivery",
    "priority": 5,
    "created_at": "2025-08-24T05:05:25.739836",
    "account": "Physics"
  },
  {
    "topic": "Why do we have seasons on Earth?",
    "tone": "explainer",
    "style": "Educational with a slightly humorous, engaging delivery",
    "priority": 5,
    "created_at": "2025-08-24T05:05:25.739836",
    "account": "Physics"
  },
  {
    "topic": "What\u2019s the secret behind a magician\u2019s tricks?",
    "tone": "explainer",
    "style": "Educational with a slightly humorous, engaging delivery",
    "priority": 5,
    "created_at": "2025-08-24T05:05:25.739836",
    "account": "Physics"
  },
  {
    "topic": "How do magnets work without touching?",
    "tone": "explainer",
    "style": "Educational with a slightly humorous, engaging delivery",
    "priority": 5,
    "created_at": "2025-08-24T05:05:25.739836",
    "account": "Physics"
  },
  {
    "topic": "What is the speed of dark?",
    "tone": "explainer",
    "style": "Educational with a slightly humorous, engaging delivery",
    "priority": 5,
    "created_at": "2025-08-24T05:05:25.739836",
    "account": "Physics"
  },
  {
    "topic": "How does static electricity work?",
    "tone": "explainer",
    "style": "Educational with a slightly humorous, engaging delivery",
    "priority": 5,
    "created_at": "2025-08-24T05:05:25.739836",
    "account": "Physics"
  },
  {
    "topic": "Why do we get shocked by doorknobs?",
    "tone": "explainer",
    "style": "Educational with a slightly humorous, engaging delivery",
    "priority": 5,
    "created_at": "2025-08-24T05:05:25.739836",
    "account": "Physics"
  }
]